crossplain/__init__.py
crossplain/directives.py
crossplain/test_crossplain.py
crossplain/test_utils.py
crossplain/utils.py
crossplain-0.6.0.dist-info/WHEEL
crossplain-0.6.0.dist-info/METADATA
crossplain-0.6.0.dist-info/RECORD
